flet_timer/__init__.py
flet_timer/flet_timer.py
flet_timer-0.0.13.dist-info/LICENSE
flet_timer-0.0.13.dist-info/METADATA
flet_timer-0.0.13.dist-info/WHEEL
flet_timer-0.0.13.dist-info/top_level.txt
flet_timer-0.0.13.dist-info/RECORD
